matplotlab/__init__.py
matplotlab/ann/__init__.py
matplotlab/ann/_code_inspector.py
matplotlab/ann/_lab_code.py
matplotlab/ann/_utils.py
matplotlab/ann/adaline_numpy.py
matplotlab/ann/adaline_pytorch.py
matplotlab/ann/autoencoder.py
matplotlab/ann/cnn.py
matplotlab/ann/cnn_filters.py
matplotlab/ann/lab_flows.py
matplotlab/ann/lstm.py
matplotlab/ann/mlp.py
matplotlab/ann/perceptron.py
matplotlab/ann/rnn.py
matplotlab/ann/tensors.py
matplotlab/ann/transfer_learning.py
matplotlab/krr/__init__.py
matplotlab/krr/_lab_code.py
matplotlab/krr/lab_flows.py
matplotlab/rl/__init__.py
matplotlab/rl/_code_inspector.py
matplotlab/rl/_lab_code.py
matplotlab/rl/_utils.py
matplotlab/rl/environments.py
matplotlab/rl/lab10_function_approximation.py
matplotlab/rl/lab11_batch_rl.py
matplotlab/rl/lab12_dqn.py
matplotlab/rl/lab7_mc_vs_td.py
matplotlab/rl/lab8_qlearning_fa.py
matplotlab/rl/lab9_offpolicy_mc.py
matplotlab/rl/lab_flows.py
matplotlab/rl/mdp.py
matplotlab/rl/monte_carlo.py
matplotlab/rl/oel2_comprehensive.py
matplotlab/rl/policy_eval.py
matplotlab/rl/policy_iter.py
matplotlab/rl/td_learning.py
matplotlab/rl/value_iter.py
matplotlab/rl/visualization.py
matplotlab/sp/__init__.py
matplotlab/sp/_code_inspector.py
matplotlab/sp/_lab_code.py
matplotlab/sp/_utils.py
matplotlab/sp/audio_basics.py
matplotlab/sp/audio_processing.py
matplotlab/sp/complex_oel.py
matplotlab/sp/dataset_utils.py
matplotlab/sp/lab8_recognition.py
matplotlab/sp/lab9_hmm.py
matplotlab/sp/lab_flows.py
matplotlab/sp/mfcc_features.py
matplotlab/sp/mfcc_reference.py
matplotlab/sp/spectrograms.py
matplotlab/sp/vowel_synthesis.py
matplotlab-0.1.14.dist-info/licenses/LICENSE
matplotlab-0.1.14.dist-info/METADATA
matplotlab-0.1.14.dist-info/WHEEL
matplotlab-0.1.14.dist-info/top_level.txt
matplotlab-0.1.14.dist-info/RECORD
