Metadata-Version: 2.4
Name: matplotlab
Version: 0.1.14
Summary: Extended plotting and ML utilities library - Now with 10 ANN Labs (Autoencoders, RNN, LSTM)
Home-page: https://github.com/Sohail-Creates/matplotlab
Author: Sohail-Creates
Author-email: sohailaslam7888@gmail.com
License: MIT
Classifier: Development Status :: 3 - Alpha
Classifier: Intended Audience :: Education
Classifier: Topic :: Scientific/Engineering :: Artificial Intelligence
Classifier: License :: OSI Approved :: MIT License
Classifier: Programming Language :: Python :: 3
Classifier: Programming Language :: Python :: 3.7
Classifier: Programming Language :: Python :: 3.8
Classifier: Programming Language :: Python :: 3.9
Classifier: Programming Language :: Python :: 3.10
Requires-Python: >=3.7
License-File: LICENSE
Requires-Dist: numpy>=1.21.0
Provides-Extra: rl
Requires-Dist: numpy>=1.21.0; extra == "rl"
Requires-Dist: matplotlib>=3.4.0; extra == "rl"
Requires-Dist: gymnasium>=0.28.0; extra == "rl"
Requires-Dist: google-generativeai>=0.3.0; extra == "rl"
Provides-Extra: ann
Requires-Dist: numpy>=1.21.0; extra == "ann"
Requires-Dist: matplotlib>=3.4.0; extra == "ann"
Requires-Dist: seaborn>=0.11.0; extra == "ann"
Requires-Dist: pandas>=1.3.0; extra == "ann"
Requires-Dist: torch>=1.9.0; extra == "ann"
Requires-Dist: torchvision>=0.10.0; extra == "ann"
Requires-Dist: tensorflow>=2.6.0; extra == "ann"
Requires-Dist: scikit-learn>=0.24.0; extra == "ann"
Requires-Dist: mlxtend>=0.19.0; extra == "ann"
Requires-Dist: Pillow>=8.0.0; extra == "ann"
Provides-Extra: sp
Requires-Dist: numpy>=1.21.0; extra == "sp"
Requires-Dist: matplotlib>=3.4.0; extra == "sp"
Requires-Dist: librosa>=0.9.0; extra == "sp"
Requires-Dist: soundfile>=0.11.0; extra == "sp"
Requires-Dist: scipy>=1.7.0; extra == "sp"
Requires-Dist: ipython>=7.0.0; extra == "sp"
Requires-Dist: google-generativeai>=0.3.0; extra == "sp"
Provides-Extra: all
Requires-Dist: numpy>=1.21.0; extra == "all"
Requires-Dist: matplotlib>=3.4.0; extra == "all"
Requires-Dist: gymnasium>=0.28.0; extra == "all"
Requires-Dist: google-generativeai>=0.3.0; extra == "all"
Requires-Dist: numpy>=1.21.0; extra == "all"
Requires-Dist: matplotlib>=3.4.0; extra == "all"
Requires-Dist: seaborn>=0.11.0; extra == "all"
Requires-Dist: pandas>=1.3.0; extra == "all"
Requires-Dist: torch>=1.9.0; extra == "all"
Requires-Dist: torchvision>=0.10.0; extra == "all"
Requires-Dist: tensorflow>=2.6.0; extra == "all"
Requires-Dist: scikit-learn>=0.24.0; extra == "all"
Requires-Dist: mlxtend>=0.19.0; extra == "all"
Requires-Dist: Pillow>=8.0.0; extra == "all"
Requires-Dist: numpy>=1.21.0; extra == "all"
Requires-Dist: matplotlib>=3.4.0; extra == "all"
Requires-Dist: librosa>=0.9.0; extra == "all"
Requires-Dist: soundfile>=0.11.0; extra == "all"
Requires-Dist: scipy>=1.7.0; extra == "all"
Requires-Dist: ipython>=7.0.0; extra == "all"
Requires-Dist: google-generativeai>=0.3.0; extra == "all"
Provides-Extra: dev
Requires-Dist: pytest>=6.0; extra == "dev"
Requires-Dist: black>=21.0; extra == "dev"
Requires-Dist: flake8>=3.9; extra == "dev"
Dynamic: author
Dynamic: author-email
Dynamic: classifier
Dynamic: description
Dynamic: description-content-type
Dynamic: home-page
Dynamic: license
Dynamic: license-file
Dynamic: provides-extra
Dynamic: requires-dist
Dynamic: requires-python
Dynamic: summary
